{"website_dir": "data/vector.co.jp/20000510073657", "website": "vector.co.jp", "cdx_entry": {"urlkey": "jp,co,vector)/", "timestamp": "20000510073657", "original": "http://www.vector.co.jp:80/", "mimetype": "text/html", "statuscode": "200", "digest": "XP4J4B3PSD5NOCH3FAERXKMFVBOIVC5L", "length": "5283"}, "image_tag": {"src": "http://www.vector.co.jp/advertise/image/a0001691/rv000501dena_0231.gif", "alt": "So-net & ISIZE \u516c\u5f0f\u30aa\u30fc\u30af\u30b7\u30e7\u30f3 \u30d3\u30c3\u30c0\u30fc\u30ba", "width": "468", "height": "60", "border": "0"}, "extension": "gif"}