{"website_dir": "data/nikkei.co.jp/20000511084722/frames/globe.nikkei.co.jp_ad_control_ng01.html", "website": "nikkei.co.jp", "cdx_entry": {"urlkey": "jp,co,nikkei,globe)/ad/control/ng01.html", "timestamp": "19990503160645", "original": "http://globe.nikkei.co.jp:80/ad/control/ng01.html", "mimetype": "text/html", "statuscode": "200", "digest": "QFZQA7YUPSOJZ64S7SZFQF3IT3YND7FM", "length": "582"}, "image_tag": {"src": "http://www.nikkei.co.jp/ad/logo/daiwa9904-b3.gif", "border": "0", "height": "60", "width": "468", "alt": "Daiwa Securities"}, "extension": null}