{"website_dir": "data/nikkeibp.co.jp/20000511101011/frames/bizad.nikkeibp.co.jp_image_ad.shtml", "website": "nikkeibp.co.jp", "cdx_entry": {"urlkey": "jp,co,nikkeibp,bizad)/image/ad.shtml", "timestamp": "19991011005522", "original": "http://bizad.nikkeibp.co.jp:80/image/ad.shtml", "mimetype": "text/html", "statuscode": "200", "digest": "ZTGZ5YUCRMDLHO353SNWHYZMRFWVZ433", "length": "586"}, "image_tag": {"src": "http://bizad.nikkeibp.co.jp/image/ng_biztech/hitachisuperh991001.gif", "border": "0", "height": "60", "width": "468", "alt": "HITACHI Click Here!"}, "extension": "gif"}